README.md
setup.py
util2/__init__.py
util2/__main__.py
util2/util2.py
util2.egg-info/PKG-INFO
util2.egg-info/SOURCES.txt
util2.egg-info/dependency_links.txt
util2.egg-info/entry_points.txt
util2.egg-info/top_level.txt
util2/datetime_extender/datetime_extender.py
util2/file/searcher.py