Metadata-Version: 2.1
Name: util2
Version: 0.0.0.4
Summary: This is utils library for Python.
Home-page: https://github.com/tanaka0079/libs/python/util2/
Author: Nishizumi
Author-email: daiman003@yahoo.co.jp
License: UNKNOWN
Keywords: util
Platform: UNKNOWN
Classifier: Development Status :: 2 - Pre-Alpha
Classifier: Natural Language :: English
Classifier: License :: OSI Approved :: MIT License
Classifier: Programming Language :: Python :: 3.8
Classifier: Operating System :: OS Independent
